setup.py
treetoreads.py
TreeToReads.egg-info/PKG-INFO
TreeToReads.egg-info/SOURCES.txt
TreeToReads.egg-info/dependency_links.txt
TreeToReads.egg-info/requires.txt
TreeToReads.egg-info/top_level.txt