Metadata-Version: 1.0
Name: TreeToReads
Version: 0.0.2
Summary: A random test lib
Home-page: https://github.com/snacktavish/TreeToReads
Author: Emily Jane McTavish  
Author-email: ejmctavish@gmail.com
License: No copyright
Platform: UNKNOWN
